cutest/__init__.py
cutest/__main__.py
cutest/_version.py
cutest/stream.py
cutest/util.py
cutest-0.0.2.dist-info/LICENSE
cutest-0.0.2.dist-info/METADATA
cutest-0.0.2.dist-info/WHEEL
cutest-0.0.2.dist-info/entry_points.txt
cutest-0.0.2.dist-info/top_level.txt
cutest-0.0.2.dist-info/RECORD
